feedy.py
feedy-0.0.4.dist-info/DESCRIPTION.rst
feedy-0.0.4.dist-info/METADATA
feedy-0.0.4.dist-info/RECORD
feedy-0.0.4.dist-info/WHEEL
feedy-0.0.4.dist-info/entry_points.txt
feedy-0.0.4.dist-info/metadata.json
feedy-0.0.4.dist-info/top_level.txt
feedy_plugins/__init__.py
feedy_plugins/social_share.py
feedy_utils/__init__.py
feedy_utils/image_downloader.py
feedy_utils/word_counter.py
tests/__init__.py
tests/test_parse_entry.py
