Metadata-Version: 2.0
Name: feedy
Version: 0.0.4
Summary: Simple RSS feed fetching framework
Home-page: https://github.com/c-bata/feedy
Author: Masashi Shibata <contact@c-bata.link>
Author-email: contact@c-bata.link
License: MIT License
Keywords: rss feed
Platform: UNKNOWN
Classifier: Development Status :: 1 - Planning
Classifier: Environment :: Console
Classifier: Intended Audience :: Developers
Classifier: License :: OSI Approved :: MIT License
Classifier: Programming Language :: Python
Classifier: Programming Language :: Python :: 3 :: Only
Classifier: Programming Language :: Python :: 3.4
Classifier: Programming Language :: Python :: 3.5
Requires-Dist: aiohttp
Requires-Dist: click
Requires-Dist: feedparser
